unsigned_generator/__init__.py
unsigned_generator/constants.py
unsigned_generator/schema.py
unsigned_generator/setup.py
unsigned_generator/unsigned_gen.py
unsigned_generator/utils.py
unsignedgen-1.0.0.dist-info/licenses/LICENSE
unsignedgen-1.0.0.dist-info/METADATA
unsignedgen-1.0.0.dist-info/WHEEL
unsignedgen-1.0.0.dist-info/top_level.txt
unsignedgen-1.0.0.dist-info/RECORD
